{
  "update": {
    "title": "更新",
    "description": "新版本已推出！",
    "descriptionLink": "更新了些什么呢？",
    "button": "更新"
  },
  "error": {
    "title": "错误",
    "description": "出错了...已将错误发送给开发者。",
    "button": "确认"
  },
  "install": {
    "title": "安装",
    "description": "安装此应用程序，以便更方便的使用。",
    "button": "安装"
  },
  "newsChannel": {
    "title": "频道",
    "description": "加入 TgStorage 频道，随时了解最新动态。",
    "button": "加入"
  },
  "sponsorship": {
    "title": "赞助",
    "description": "很遗憾，如果没有您的参与，我们将无法继续开发该应用程序。每月只需 1 欧元，我就可以继续开发。",
    "button": "赞助商"
  }
}
